pypwdgen/__init__.py
pypwdgen/__main__.py
pypwdgen/cli.py
pypwdgen/config.py
pypwdgen/core.py
pypwdgen-1.0.4.dist-info/LICENSE
pypwdgen-1.0.4.dist-info/METADATA
pypwdgen-1.0.4.dist-info/WHEEL
pypwdgen-1.0.4.dist-info/top_level.txt
pypwdgen-1.0.4.dist-info/RECORD
