Metadata-Version: 2.1
Name: pypwdgen
Version: 1.0.4
Summary: Complex password generator
Home-page: https://github.com/polluxtroy3758/pypwdgen
Author: polluxtroy3758
Author-email: 2147396+polluxtroy3758@users.noreply.github.com
License: UNKNOWN
Project-URL: Bug Tracker, https://github.com/polluxtroy3758/pypwdgen/issues
Platform: UNKNOWN
Classifier: Programming Language :: Python :: 3
Classifier: Programming Language :: Python :: 3.6
Classifier: Programming Language :: Python :: 3.7
Classifier: Programming Language :: Python :: 3.8
Classifier: Programming Language :: Python :: 3.9
Classifier: License :: OSI Approved :: MIT License
Classifier: Operating System :: OS Independent
Classifier: Topic :: Security
Classifier: Topic :: Utilities
Requires-Python: >=3.6
License-File: LICENSE
